Workbook

Sheet Read Me
B1: Chokro — Budget Plan
B2: Soft launch: 30 September 2026 · Dhaka pilot · Prepared 2 September 2026
B4: What this is | C4: A complete cost picture for taking Chokro from its current state to a soft launch on 30 September 2026, and through the first twelve months of operation at Dhaka pilot scale. Three cost categories: business registration, technology, and hired expertise. Each has its own tab. The Budget Summary tab is the one-page answer.
B6: Who it is for | C6: Sponsors and funders. It is written to be read by someone who has not seen the codebase, and every figure traces to a named source on the Sources tab.
B8: The one thing to read first | C8: Costs here are split into ONE-TIME, ANNUAL and MONTHLY, and they are never added together without the period stated. This matters: the largest technology line, Cloudinary at ৳12,198, is a MONTHLY charge that happens to equal the ANNUAL Apple Developer fee. Read as a flat list, this budget looks like ৳36,000. It is ৳2.89 lakh in year one.
B10: How to read the colours | C10: BLUE text is a hardcoded input or a lever you can change. BLACK text is a formula. GREEN text pulls a figure from another tab. A pale yellow cell is a key assumption worth arguing with. Change the exchange rate on Assumptions!B6 and the entire workbook re-prices.
B12: Scenario shown | C12: Base case is ANDROID-FIRST at soft launch, sole-proprietorship registration, and $400 of hired specialist time. The Decisions tab prices the alternatives — including iOS at launch, which adds ৳1.32 lakh.
B14: What is decided and what is not | C14: DECIDED by Arnish: sole proprietorship; $400 one-time expert budget; Gemini 2.5 Flash-Lite on the paid tier as the screening provider; Dhaka pilot of a few wards and campuses. NOT DECIDED: whether a Mac is available for iOS builds; whether the trademark is filed before launch; when the Cloudinary migration happens. All three are priced on Decisions.
B16: Relationship to the other Chokro workbooks | C16: This is the money view. Chokro_Technology_Cost_Model.xlsx holds the per-vendor engineering detail and the city/national scale-up; Chokro_Soft_Launch_Planner_Sep2026.xlsx holds the schedule. Where they disagree with this file, this file is newer — it corrects the screening provider from Groq to Gemini and adds Sentry.
B19: Tabs in order
B20: Assumptions | C20: Every driver and vendor rate. Change things here.
B21: Budget Summary | C21: The one-page total: to launch, year 1, year 2 onward.
B22: 1 Registration | C22: Sole-proprietorship registration and licensing.
B23: 2 Technology | C23: Stores, domains, hosting, AI screening, monitoring.
B24: 3 People | C24: The $400 expert budget against the 35 must-do days.
B25: Run Rate | C25: The monthly recurring stack, and how it grows with scale.
B26: Cash Flow | C26: Month by month, Sep 2026 to Aug 2027.
B27: Decisions | C27: Five costed levers, each with a recommendation.
B28: Risks | C28: Budget risks, with the taka amount at stake.
B29: Sources | C29: Every rate, where it came from, and when it was checked.

Sheet Budget Summary
A1: Budget Summary
A2: Chokro · soft launch 30 September 2026 · Dhaka pilot · base case is Android-first, sole proprietorship, $400 of hired expertise.
A4: The headline
B5: BDT | C5: USD | E5: What it covers
A6: To launch — all of September 2026 | B6: ='Cash Flow'!B12 -> 83359.689 | C6: =B6/Assumptions!$B$6 -> 676.56593 | E6: Registration, the Play account, both domains, the entire expert budget and the first month of the technology stack. September carries almost every fixed cost in the year.
A7: Year one — Sep 2026 to Aug 2027 | B7: ='Cash Flow'!N12 -> 289163.51 | C7: =B7/Assumptions!$B$6 -> 2346.9159 | E7: Everything above plus eleven more months of the technology stack.
A8: Year two onward — per year | B8: ='1 Registration'!B28+'2 Technology'!B33 -> 234064.26 | C8: =B8/Assumptions!$B$6 -> 1899.7181 | E8: Licence renewals, both domains and twelve months of technology. No one-time costs, no expert budget.
A10: By category — year one
A11: Category | B11: BDT | C11: USD | D11: Share | E11: Note
A12: 1 — Business registration | B12: ='1 Registration'!B26 -> 8587 | C12: =B12/Assumptions!$B$6 -> 69.694018 | D12: =IFERROR(B12/$B$15,0) -> 0.029696001 | E12: Sole proprietorship. Small because the trade licence IS the registration.
A13: 2 — Technology | B13: ='2 Technology'!B31 -> 231292.51 | C13: =B13/Assumptions!$B$6 -> 1877.2219 | D13: =IFERROR(B13/$B$15,0) -> 0.79986756 | E13: 97% of this is the recurring monthly stack, and two thirds of that is Cloudinary alone.
A14: 3 — Hired expertise | B14: ='3 People'!C33 -> 49284 | C14: =B14/Assumptions!$B$6 -> 400 | D14: =IFERROR(B14/$B$15,0) -> 0.17043644 | E14: $400 one-time, funding 11 of the 35 days that must happen before launch.
A15: Total year one | B15: =SUM(B12:B14) -> 289163.51 | C15: =B15/Assumptions!$B$6 -> 2346.9159 | D15: =SUM(D12:D14) -> 1
A16: Cross-check against the Cash Flow tab (should be zero) | B16: =B15-'Cash Flow'!N12 -> 0 | E16: The categories and the month-by-month view are built from the same cells, so any difference here means a broken reference.
A18: Scenarios — year one
A19: Scenario | B19: BDT | C19: USD | D19: vs base | E19: Note
A20: Base case — this workbook | B20: ='Cash Flow'!N12 -> 289163.51 | C20: =B20/Assumptions!$B$6 -> 2346.9159 | D20: =B20-$B$20 -> 0 | E20: Android-first, sole proprietorship, $400 of expertise, 24 days of founder time.
A21: + trademark filed | B21: =B20+'1 Registration'!B24 -> 297663.51 | C21: =B21/Assumptions!$B$6 -> 2415.9038 | D21: =B21-$B$20 -> 8500 | E21: Add before a sponsor's logo goes anywhere near the brand.
A22: + iOS at launch | B22: =B20+'2 Technology'!B7+'2 Technology'!B14 -> 421361.3 | C22: =B22/Assumptions!$B$6 -> 3419.8629 | D22: =B22-$B$20 -> 132197.79 | E22: Mac plus the Apple Developer Program. Also adds 5–14 days of D-U-N-S wait to the critical path.
A23: + the 24-day gap closed | B23: =B20+'3 People'!C24 -> 403163.51 | C23: =B23/Assumptions!$B$6 -> 3272.1655 | D23: =B23-$B$20 -> 114000 | E23: One more contractor month. Removes the plan's single largest dependency.
A24: All of the above | B24: =B20+'1 Registration'!B24+'2 Technology'!B7+'2 Technology'!B14+'3 People'!C24 -> 543861.3 | C24: =B24/Assumptions!$B$6 -> 4414.1003 | D24: =B24-$B$20 -> 254697.79 | E24: The fully-resourced version of the same launch.
A26: Funding ask
A27: Ask | B27: BDT | C27: USD | E27: What the money unlocks
A28: Already committed by the founder | B28: ='Cash Flow'!N12 -> 289163.51 | C28: =B28/Assumptions!$B$6 -> 2346.9159 | E28: A soft launch on 30 September 2026: Android, Dhaka pilot across 3–5 anchor wards and campuses, the security and audit lanes closed by a specialist, and a production-grade screening provider.
A29: Close the engineering gap | B29: ='3 People'!C24 -> 114000 | C29: =B29/Assumptions!$B$6 -> 925.24957 | E29: All 35 pre-launch days done by a specialist instead of 24 of them by the founder. Buys back the founder's September for pilot operations, ward partnerships and sponsor conversations — which is where a sponsor's money compounds fastest.
A30: iOS at launch | B30: ='2 Technology'!B7+'2 Technology'!B14 -> 132197.79 | C30: =B30/Assumptions!$B$6 -> 1072.9469 | E30: iOS users from day one rather than a later release. Matters for institutional and corporate pilots more than for ward residents.
A31: Bring the Cloudinary migration forward | B31: =Decisions!B7 -> 28500 | C31: =B31/Assumptions!$B$6 -> 231.31239 | E31: Cuts the monthly run rate by about two thirds, permanently, and pays for itself in under three months. The cheapest durable improvement to Chokro's unit economics available right now.
A32: Fully funded year one | B32: =SUM(B28:B31) -> 563861.3 | C32: =B32/Assumptions!$B$6 -> 4576.4248
A34: What this budget is not hiding: $400 of hired expertise against 35 days of necessary work means 24 of those days are founder time, and the plan has no redundancy if that time disappears. The $400 has been pointed at the three lanes that cannot be corrected quietly after launch — unrun security and audit lanes, a real-device pass, and replacing a preview-grade AI dependency — so a slip delays polish rather than exposing users. Every estimate that has not been quoted is marked as such on the Sources tab.

Sheet Assumptions
A1: Assumptions & Rates
A2: Blue cells are inputs — change them and every tab re-prices. Yellow cells are the assumptions most worth challenging.
A4: Currency and scale
A5: Driver | B5: Value | E5: Basis
A6: USD / BDT exchange rate | B6: 123.21 | E6: Bangladesh Bank mid-rate band, checked 30 Aug 2026. The single most load-bearing cell in this workbook.
A7: Soft launch date | B7: 30 Sep 2026 | E7: Arnish, 29 Aug 2026.
A8: Pilot registered users | B8: 5000 | E8: Dhaka pilot target across 3–5 anchor wards / campuses.
A9: Monthly active rate | B9: 0.3 | E9: Assumption carried from the technology cost model.
A10: Monthly active users | B10: =B8*B9 -> 1500
A11: Screenings per active user / month | B11: 5 | E11: 4 disposals + 1 reward claim. Each is one vision-API call.
A12: Screenings per month | B12: =B10*B11 -> 7500
A14: Labour — Dhaka freelance specialist, per day
A15: Rate band | B15: BDT / day | C15: USD / day | E15: Basis
A16: Low | B16: 3500 | C16: =B16/Assumptions!$B$6 -> 28.406785 | E16: Derived from Dhaka mid/senior salary bands (৳30k–250k/mo) plus a freelance premium. See Sources.
A17: Mid — used throughout this plan | B17: 4750 | C17: =B17/Assumptions!$B$6 -> 38.552066 | E17: Derived from Dhaka mid/senior salary bands (৳30k–250k/mo) plus a freelance premium. See Sources.
A18: High | B18: 6000 | C18: =B18/Assumptions!$B$6 -> 48.697346 | E18: Derived from Dhaka mid/senior salary bands (৳30k–250k/mo) plus a freelance premium. See Sources.
A19: Working days per month | B19: 22 | E19: Sunday–Thursday working week.
A21: Vendor rates
A22: Item | B22: Unit | C22: USD | D22: BDT | E22: Basis
A23: Cloudinary Plus | B23: per month | C23: 99 | D23: =C23*Assumptions!$B$6 -> 12197.79 | E23: 225 credits. Free tier is 25 and the pilot burns ~63 in month one.
A24: Gemini 2.5 Flash-Lite (paid tier) | B24: per screening | C24: 0.00026 | D24: =C24*Assumptions!$B$6 -> 0.0320346 | E24: 2,000 in + 150 out tokens per call, Vertex AI paid tier.
A25: Render Starter — app server | B25: per month | C25: 25 | D25: =C25*Assumptions!$B$6 -> 3080.25 | E25: Always-on Node instance.
A26: Sentry Team — error monitoring | B26: per month | C26: 25.9 | D26: =C26*Assumptions!$B$6 -> 3191.139 | E26: Arnish, 2 Sep 2026.
A27: Firebase Blaze at pilot scale | B27: per month | C27: 0 | D27: =C27*Assumptions!$B$6 -> 0 | E27: Auth free to 50k MAU; Firestore reads ~free; 100 GB egress free.
A28: Redis — Upstash free tier | B28: per month | C28: 0 | D28: =C28*Assumptions!$B$6 -> 0 | E28: Required before a second server instance, not before.
A29: Apple Developer Program | B29: per year | C29: 99 | D29: =C29*Assumptions!$B$6 -> 12197.79 | E29: Deferrable — see Decisions.
A30: Google Play developer account | B30: one-time | C30: 25 | D30: =C30*Assumptions!$B$6 -> 3080.25 | E30: One-time, non-refundable.
A31: .com domain | B31: per year | C31: =D31/Assumptions!$B$6 -> 9.731353 | D31: 1199 | E31: Local registrar.
A32: .com.bd domain | B32: per year | C32: =D32/Assumptions!$B$6 -> 20.290561 | D32: 2500 | E32: BTCL.
A33: Mac mini for iOS builds | B33: one-time | C33: =D33/Assumptions!$B$6 -> 973.94692 | D33: 120000 | E33: ESTIMATE — Arnish has not confirmed whether a Mac is available.
A35: Note on the screening provider: Arnish's draft budget listed Groq vision at ৳1,525/month. Groq's qwen vision model is PREVIEW-only and Groq's production catalogue contains no vision model at all, so it cannot carry a live app. This workbook prices Gemini 2.5 Flash-Lite on the paid tier instead — 6.3× cheaper and generally available. The paid tier is not a cost choice but a consent one: on Google's unpaid tier, human reviewers may read submitted content, and Chokro submits user photographs tied to GPS and identity.

Sheet 1 Registration
A1: Category 1 — Business Registration
A2: Sole proprietorship, Dhaka North City Corporation. Figures supplied by Arnish, 2 Sep 2026, except where noted.
A4: One-time
A5: Item | B5: BDT | C5: USD | E5: Note
A6: Licence book / form / processing | B6: 385 | C6: =B6/Assumptions!$B$6 -> 3.1247464 | E6: Midpoint of Arnish's ৳270–500 range.
A7: Documentation and photocopy | B7: 350 | C7: =B7/Assumptions!$B$6 -> 2.8406785 | E7: Midpoint of Arnish's ৳200–500 range.
A8: Bank account opening — minimum balance | B8: 2000 | C8: =B8/Assumptions!$B$6 -> 16.232449 | E8: Current-account minimum. Recoverable, but it is cash you cannot spend.
A9: e-TIN registration | B9: 0 | C9: =B9/Assumptions!$B$6 -> 0 | E9: Free, NBR online. Still required.
A10: BIN / VAT registration (Mushak 2.1) | B10: 0 | C10: =B10/Assumptions!$B$6 -> 0 | E10: Free, NBR online. Required to invoice EPR clients.
A11: D-U-N-S number | B11: 0 | C11: =B11/Assumptions!$B$6 -> 0 | E11: Free, 5–14 days. Only needed if an Apple company account is opened.
A12: Total one-time | B12: =SUM(B6:B11) -> 2735 | C12: =B12/Assumptions!$B$6 -> 22.197874
A14: Annual — these renew every year
A15: Item | B15: BDT / year | C15: USD / year | E15: Note
A16: DNCC Trade Licence fee — Category 253 | B16: 2000 | C16: =B16/Assumptions!$B$6 -> 16.232449 | E16: Arnish. Annual renewal, not a one-time cost.
A17: Signboard tax | B17: 480 | C17: =B17/Assumptions!$B$6 -> 3.8957877 | E17: Applies if a signboard is displayed.
A18: VAT on licence fees | B18: =0.15*(B16+B17) -> 372 | C18: =B18/Assumptions!$B$6 -> 3.0192355 | E18: 15% of licence fee plus signboard tax. Reproduces Arnish's ৳372 exactly.
A19: Source tax | B19: 3000 | C19: =B19/Assumptions!$B$6 -> 24.348673 | E19: Arnish notes this depends on applicable rules — treat as annual and confirm with the ward office.
A20: Total annual | B20: =SUM(B16:B19) -> 5852 | C20: =B20/Assumptions!$B$6 -> 47.496145
A22: Optional but recommended
A23: Item | B23: BDT | C23: USD | E23: Note
A24: Trademark registration — চক্র / Chokro, one class | B24: 8500 | C24: =B24/Assumptions!$B$6 -> 68.987907 | E24: ≈৳3,500 government fee plus ≈৳5,000 agent fee, one class, DPDT. ESTIMATE — not yet quoted. File before a sponsor's logo appears next to the brand: association is the thing they are buying.
A26: CATEGORY 1 — YEAR ONE TOTAL (excl. trademark) | B26: =B12+B20 -> 8587 | C26: =B26/Assumptions!$B$6 -> 69.694018
A27: CATEGORY 1 — YEAR ONE TOTAL (incl. trademark) | B27: =B26+B24 -> 17087 | C27: =B27/Assumptions!$B$6 -> 138.68193
A28: CATEGORY 1 — YEAR TWO ONWARD, per year | B28: =B20 -> 5852 | C28: =B28/Assumptions!$B$6 -> 47.496145
A30: Why this category is small: as a sole proprietorship the trade licence IS the registration. A private limited company would add RJSC name clearance, incorporation, stamp duty scaled to authorised capital and agent fees — roughly ৳15,000–40,000 more. Arnish chose sole proprietorship on 2 Sep 2026. Worth revisiting before signing an EPR compliance contract, because a limited company limits personal liability and most corporate procurement departments prefer one.

Sheet 2 Technology
A1: Category 2 — Technology
A2: Priced at Dhaka pilot scale: 5,000 registered users, 1,500 monthly active, 7,500 screenings per month.
A4: One-time
A5: Item | B5: BDT | C5: USD | D5: In base case? | E5: Note
A6: Google Play developer account | B6: =Assumptions!D30 -> 3080.25 | C6: =B6/Assumptions!$B$6 -> 25 | D6: Yes | E6: One-time, non-refundable. Required for the Android launch.
A7: Mac mini for iOS builds | B7: =Assumptions!D33 -> 120000 | C7: =B7/Assumptions!$B$6 -> 973.94692 | D7: DEFERRED | E7: You cannot build or submit an iOS app without one. Excluded from the base case — see Decisions, lever 1.
A8: D-U-N-S number | B8: 0 | C8: =B8/Assumptions!$B$6 -> 0 | D8: n/a | E8: Free. Only on the iOS path.
A9: Total one-time — base case (Android-first) | B9: =B6+B8 -> 3080.25 | C9: =B9/Assumptions!$B$6 -> 25
A10: Total one-time — with iOS | B10: =SUM(B6:B8) -> 123080.25 | C10: =B10/Assumptions!$B$6 -> 998.94692
A12: Annual
A13: Item | B13: BDT / year | C13: USD / year | D13: In base case? | E13: Note
A14: Apple Developer Program | B14: =Assumptions!D29 -> 12197.79 | C14: =B14/Assumptions!$B$6 -> 99 | D14: DEFERRED | E14: Renews annually. Excluded from the base case with the Mac.
A15: .com domain | B15: =Assumptions!D31 -> 1199 | C15: =B15/Assumptions!$B$6 -> 9.731353 | D15: Yes | E15: Marketing site.
A16: .com.bd domain | B16: =Assumptions!D32 -> 2500 | C16: =B16/Assumptions!$B$6 -> 20.290561 | D16: Yes | E16: Local credibility, and it matters to Bangladeshi institutional clients.
A17: Total annual — base case | B17: =B15+B16 -> 3699 | C17: =B17/Assumptions!$B$6 -> 30.021914
A18: Total annual — with iOS | B18: =SUM(B14:B16) -> 15896.79 | C18: =B18/Assumptions!$B$6 -> 129.02191
A20: Monthly — the recurring stack at pilot scale
A21: Item | B21: BDT / month | C21: USD / month | D21: Share of stack | E21: Note
A22: Image hosting — Cloudinary Plus | B22: =Assumptions!D23 -> 12197.79 | C22: =B22/Assumptions!$B$6 -> 99 | D22: =IFERROR(B22/$B$28,0) -> 0.65195917 | E22: Storage, bandwidth and on-the-fly derivations. The single largest line in the whole budget.
A23: AI screening — Gemini 2.5 Flash-Lite | B23: =Assumptions!D24*Assumptions!$B$12 -> 240.2595 | C23: =B23/Assumptions!$B$6 -> 1.95 | D23: =IFERROR(B23/$B$28,0) -> 0.01284162 | E23: One call per disposal and per reward claim. Scales linearly with volume, no economy of scale.
A24: App server — Render Starter | B24: =Assumptions!D25 -> 3080.25 | C24: =B24/Assumptions!$B$6 -> 25 | D24: =IFERROR(B24/$B$28,0) -> 0.16463615 | E24: Always-on Node instance.
A25: Error monitoring — Sentry Team | B25: =Assumptions!D26 -> 3191.139 | C25: =B25/Assumptions!$B$6 -> 25.9 | D25: =IFERROR(B25/$B$28,0) -> 0.17056306 | E25: Arnish, 2 Sep 2026.
A26: Firebase Blaze — Auth, Firestore, Storage | B26: =Assumptions!D27 -> 0 | C26: =B26/Assumptions!$B$6 -> 0 | D26: =IFERROR(B26/$B$28,0) -> 0 | E26: ৳0 at pilot but a billing account with a card on file is required from day one. Auth becomes ~$505/mo at 150k MAU — see Risks.
A27: Redis — Upstash free tier | B27: =Assumptions!D28 -> 0 | C27: =B27/Assumptions!$B$6 -> 0 | D27: =IFERROR(B27/$B$28,0) -> 0 | E27: ৳0 at pilot on a single instance. Becomes mandatory the moment a second instance runs — see Risks.
A28: Total monthly | B28: =SUM(B22:B27) -> 18709.439 | C28: =B28/Assumptions!$B$6 -> 151.85 | D28: =SUM(D22:D27) -> 1
A29: Total monthly × 12 | B29: =B28*12 -> 224513.26 | C29: =B29/Assumptions!$B$6 -> 1822.2
A31: CATEGORY 2 — YEAR ONE TOTAL (base case, Android-first) | B31: =B9+B17+B29 -> 231292.51 | C31: =B31/Assumptions!$B$6 -> 1877.2219
A32: CATEGORY 2 — YEAR ONE TOTAL (with iOS at launch) | B32: =B10+B18+B29 -> 363490.3 | C32: =B32/Assumptions!$B$6 -> 2950.1688
A33: CATEGORY 2 — YEAR TWO ONWARD, per year (base case) | B33: =B17+B29 -> 228212.26 | C33: =B33/Assumptions!$B$6 -> 1852.2219
A35: Unit convention: every figure above is labelled with its period. This is not pedantry. Cloudinary at ৳12,198 per MONTH and the Apple Developer Program at ৳12,198 per YEAR are the same number for entirely different periods, and a budget that lists them in one column without units understates the year by a factor of seven.
A36: Cloudinary is roughly two thirds of the monthly stack. There is a known six-day engineering change that removes it and pays for itself in under three months. It is priced on the Decisions tab, lever 2, and deliberately scheduled AFTER launch — those six days would otherwise come out of the 35 days that have to happen before 30 September.

Sheet 3 People
A1: Category 3 — Hired Expertise
A2: Arnish has committed $400 one-time. This tab shows exactly what that buys and what it does not.
A4: The budget
C5: BDT | D5: USD | F5: Note
A6: Expert budget committed | C6: =D6*Assumptions!$B$6 -> 49284 | D6: 400 | F6: Arnish, 2 Sep 2026. One-time, total across all lanes.
A7: Day rate assumed (mid band) | C7: =Assumptions!$B$17 -> 4750 | D7: =C7/Assumptions!$B$6 -> 38.552066 | F7: Change the band on Assumptions to re-price the days funded.
A8: Specialist days this funds | C8: =IFERROR(C6/C7,0) -> 10.375579 | F8: At the low band (৳3,500/day) the same budget funds 14.1 days.
A10: What has to happen before 30 September — 35 days
A11: Lane | B11: Days | C11: Cost (৳) | D11: Cost ($) | E11: Funded by the $400? | F11: Note
A12: 35 medium UI/UX audit findings | B12: 18 | C12: =B12*Assumptions!$B$17 -> 85500 | D12: =C12/Assumptions!$B$6 -> 693.93718 | E12: Founder time | F12: Already documented finding-by-finding in UX_AUDIT_OUTSTANDING.md. The lane where Arnish's own product judgement beats a contractor's.
A13: Three unrun audit lanes | B13: 5 | C13: =B13*Assumptions!$B$17 -> 23750 | D13: =C13/Assumptions!$B$6 -> 192.76033 | E13: FUNDED | F13: Cannot be assessed after launch without exposing users first.
A14: Staging device pass | B14: 3 | C14: =B14*Assumptions!$B$17 -> 14250 | D14: =C14/Assumptions!$B$6 -> 115.6562 | E14: FUNDED | F14: Real handsets on real Dhaka networks. Catches what an emulator cannot.
A15: Store submission | B15: 4 | C15: =B15*Assumptions!$B$17 -> 19000 | D15: =C15/Assumptions!$B$6 -> 154.20826 | E15: Founder time | F15: Play production access needs 12 testers running the app for 14 consecutive days, then review.
A16: Groq → Gemini screening adapter | B16: 3 | C16: =B16*Assumptions!$B$17 -> 14250 | D16: =C16/Assumptions!$B$6 -> 115.6562 | E16: FUNDED | F16: Removes a preview-model dependency AND permanently reduces manual review volume. Best-value engineering days in the plan.
A17: Index deploy and release checklist | B17: 2 | C17: =B17*Assumptions!$B$17 -> 9500 | D17: =C17/Assumptions!$B$6 -> 77.104131 | E17: Founder time | F17: Mechanical, low risk.
A18: Total must-do before launch | B18: =SUM(B12:B17) -> 35 | C18: =SUM(C12:C17) -> 166250 | D18: =C18/Assumptions!$B$6 -> 1349.3223
A20: The funded package, and the gap
B21: Days | C21: Cost (৳) | D21: Cost ($) | F21: Note
A22: Funded by the $400 — one senior contractor | B22: =B13+B14+B16 -> 11 | C22: =C13+C14+C16 -> 52250 | D22: =C22/Assumptions!$B$6 -> 424.07272 | F22: Audit lanes, staging device pass and the Gemini adapter, given to ONE person rather than split across four. A small budget survives concentration and dies of fragmentation.
A23: Rate required to fit the funded package into $400 | C23: =IFERROR($C$6/$B$22,0) -> 4480.3636 | D23: =C23/Assumptions!$B$6 -> 36.363636 | F23: Within the ৳3,500–6,000 Dhaka band, so the package is achievable — but negotiate the rate before scoping it.
A24: Unfunded — falls to founder time | B24: =B18-B22 -> 24 | C24: =C18-C22 -> 114000 | D24: =C24/Assumptions!$B$6 -> 925.24957 | F24: 24 of the 35 days. This is the plan's single largest dependency and it has no redundancy.
A27: Manual review operator — a running cost, not a hire
A28: Stage | B28: Heads | C28: BDT / month | D28: USD / month | F28: Note
A29: Dhaka pilot — now | B29: 0.5 | C29: 0 | D29: =C29/Assumptions!$B$6 -> 0 | F29: Roughly 25 reviews a day at a minute or two each. Founder absorbs it; the budget line is ৳0.
A30: City scale — 50k users | B30: 2 | C30: 40000 | D30: =C30/Assumptions!$B$6 -> 324.64897 | F30: 2 operators at ≈৳20,000/month. This is when it becomes payroll.
A31: National — 500k users | B31: 12 | C31: 240000 | D31: =C31/Assumptions!$B$6 -> 1947.8938 | F31: Scales with disposal volume, not with users. Every screening failure routes to a human by design.
A33: CATEGORY 3 — YEAR ONE TOTAL (pilot: expert budget only) | C33: =C6 -> 49284 | D33: =C33/Assumptions!$B$6 -> 400
A35: The honest position for a sponsor: $400 funds 11 of the 35 days that have to happen before 30 September. It has been pointed at the three lanes that cannot be corrected quietly after launch — the unrun security and audit lanes, a real-device pass, and replacing a preview-grade AI dependency. The remaining 24 days rest on founder time. Closing that gap costs about $925 more; the Budget Summary tab prices it as a funding ask.

Sheet Run Rate
A1: Monthly Run Rate by Scale
A2: The pilot column is live from the Technology tab. City and national are INDICATIVE, carried from the technology cost model.
A4: USD per month
A5: Line | B5: Pilot — 5k users | C5: City — 50k users | D5: National — 500k users | E5: Note
A6: Image hosting — Cloudinary | B6: ='2 Technology'!C22 -> 99 | C6: 260 | D6: 2602 | E6: Credit-based tiers, not linear. The dominant line at every scale.
A7: AI screening — Gemini 2.5 Flash-Lite | B7: ='2 Technology'!C23 -> 1.95 | C7: 19.5 | D7: 195 | E7: Perfectly linear at $0.00026 per screening. Groq would have been 6.3× this.
A8: App server and compute | B8: ='2 Technology'!C24 -> 25 | C8: 85 | D8: 770 | E8: Render Starter → Pro → Cloud Run.
A9: Error monitoring — Sentry | B9: ='2 Technology'!C25 -> 25.9 | C9: 25.9 | D9: 129 | E9: Team tier holds to city scale; national needs a tier upgrade. ESTIMATE.
A10: Firebase Auth | B10: ='2 Technology'!C26 -> 0 | C10: 0 | D10: 505 | E10: Free to 50k MAU, then $0.0055/MAU. The cliff nobody budgets for.
A11: Firestore, Storage and egress | B11: 0 | C11: 101 | D11: 48 | E11: Firestore reads are ~free even at national. Egress is the variable part.
A12: Manual review operators | B12: ='3 People'!D29 -> 0 | C12: ='3 People'!D30 -> 324.64897 | D12: ='3 People'!D31 -> 1947.8938 | E12: From the People tab. Scales with disposal volume, not users.
A13: Total USD per month | B13: =SUM(B6:B12) -> 151.85 | C13: =SUM(C6:C12) -> 816.04897 | D13: =SUM(D6:D12) -> 6196.8938
A14: Total BDT per month | B14: =B13*Assumptions!$B$6 -> 18709.439 | C14: =C13*Assumptions!$B$6 -> 100545.39 | D14: =D13*Assumptions!$B$6 -> 763519.29
A15: Total BDT per year | B15: =B14*12 -> 224513.26 | C15: =C14*12 -> 1206544.7 | D15: =D14*12 -> 9162231.5
A17: Read this tab as a warning, not a forecast. Two lines behave badly as Chokro grows: Firebase Auth is free until 50,000 monthly active users and then costs $0.0055 each — about $505 a month at 150k MAU, appearing in a single billing cycle with no warning. And manual review operators scale with how much rubbish gets disposed of, not with how many people sign up, so they are the line that turns a software margin into a services margin. Both are structural, and both are cheaper to design around now than to discover later.

Sheet Cash Flow
A1: Cash Flow — September 2026 to August 2027
A2: Base case: Android-first, sole proprietorship, $400 expert budget. All figures BDT.
A5: Line | B5: Sep 26 | C5: Oct 26 | D5: Nov 26 | E5: Dec 26 | F5: Jan 27 | G5: Feb 27 | H5: Mar 27 | I5: Apr 27 | J5: May 27 | K5: Jun 27 | L5: Jul 27 | M5: Aug 27 | N5: Year 1 total
A6: Registration — one-time | B6: ='1 Registration'!B12 -> 2735 | C6: 0 | D6: 0 | E6: 0 | F6: 0 | G6: 0 | H6: 0 | I6: 0 | J6: 0 | K6: 0 | L6: 0 | M6: 0 | N6: =SUM(B6:M6) -> 2735
A7: Registration — annual licences | B7: ='1 Registration'!B20 -> 5852 | C7: 0 | D7: 0 | E7: 0 | F7: 0 | G7: 0 | H7: 0 | I7: 0 | J7: 0 | K7: 0 | L7: 0 | M7: 0 | N7: =SUM(B7:M7) -> 5852
A8: Google Play account | B8: ='2 Technology'!B6 -> 3080.25 | C8: 0 | D8: 0 | E8: 0 | F8: 0 | G8: 0 | H8: 0 | I8: 0 | J8: 0 | K8: 0 | L8: 0 | M8: 0 | N8: =SUM(B8:M8) -> 3080.25
A9: Domains — annual | B9: ='2 Technology'!B17 -> 3699 | C9: 0 | D9: 0 | E9: 0 | F9: 0 | G9: 0 | H9: 0 | I9: 0 | J9: 0 | K9: 0 | L9: 0 | M9: 0 | N9: =SUM(B9:M9) -> 3699
A10: Hired expertise | B10: ='3 People'!C6 -> 49284 | C10: 0 | D10: 0 | E10: 0 | F10: 0 | G10: 0 | H10: 0 | I10: 0 | J10: 0 | K10: 0 | L10: 0 | M10: 0 | N10: =SUM(B10:M10) -> 49284
A11: Technology — monthly stack | B11: ='2 Technology'!$B$28 -> 18709.439 | C11: ='2 Technology'!$B$28 -> 18709.439 | D11: ='2 Technology'!$B$28 -> 18709.439 | E11: ='2 Technology'!$B$28 -> 18709.439 | F11: ='2 Technology'!$B$28 -> 18709.439 | G11: ='2 Technology'!$B$28 -> 18709.439 | H11: ='2 Technology'!$B$28 -> 18709.439 | I11: ='2 Technology'!$B$28 -> 18709.439 | ... M11: ='2 Technology'!$B$28 -> 18709.439 | N11: =SUM(B11:M11) -> 224513.26
A12: TOTAL OUT | B12: =B6+B7+B8+B9+B10+B11 -> 83359.689 | C12: =C6+C7+C8+C9+C10+C11 -> 18709.439 | D12: =D6+D7+D8+D9+D10+D11 -> 18709.439 | E12: =E6+E7+E8+E9+E10+E11 -> 18709.439 | F12: =F6+F7+F8+F9+F10+F11 -> 18709.439 | G12: =G6+G7+G8+G9+G10+G11 -> 18709.439 | H12: =H6+H7+H8+H9+H10+H11 -> 18709.439 | I12: =I6+I7+I8+I9+I10+I11 -> 18709.439 | ... M12: =M6+M7+M8+M9+M10+M11 -> 18709.439 | N12: =SUM(B12:M12) -> 289163.51
A13: Cumulative | B13: =B12 -> 83359.689 | C13: =B13+C12 -> 102069.13 | D13: =C13+D12 -> 120778.57 | E13: =D13+E12 -> 139488 | F13: =E13+F12 -> 158197.44 | G13: =F13+G12 -> 176906.88 | H13: =G13+H12 -> 195616.32 | I13: =H13+I12 -> 214325.76 | J13: =I13+J12 -> 233035.2 | ... M13: =L13+M12 -> 289163.51 | N13: =M13 -> 289163.51
A15: Optional additions — not included in the totals above
A16: Item | B16: BDT | C16: When | N16: Note
A17: Trademark — চক্র / Chokro | B17: ='1 Registration'!B24 -> 8500 | C17: Before first sponsor logo | N17: Cheap insurance on the one asset a sponsor is buying association with.
A18: Mac mini + Apple Developer (iOS path) | B18: ='2 Technology'!B7+'2 Technology'!B14 -> 132197.79 | C18: Only if iOS at launch | N18: Deferred in the base case. See Decisions, lever 1.
A19: Closing the 24-day founder-time gap | B19: ='3 People'!C24 -> 114000 | C19: September | N19: One more contractor month. Priced as a funding ask on Budget Summary.
A22: September carries almost the entire fixed cost of the year — registration, the store account, both domains and the whole expert budget land in the launch month, on top of the first month of the technology stack. From October the business burns a flat monthly rate. If cash is tight, the two domains and the trademark are the only lines that can slip without touching the launch.

Sheet Decisions
A1: Five Costed Decisions
A2: Each lever is priced. The recommendation column is the position this budget takes; the reasoning is there so it can be argued with.
A4: Lever | B4: One-off cost (৳) | C4: Saving (৳/month) | D4: Year-1 effect (৳) | E4: Payback | F4: Recommendation | G4: Why
A5: Cloudinary replacement cost after migration (৳/month) | B5: 150 | G5: Firebase Storage plus a CDN at pilot volume. Input used by lever 2.
A6: 1 — Launch Android-first, defer iOS | B6: 0 | C6: 0 | D6: =-('2 Technology'!B7+'2 Technology'!B14) -> -132197.79 | E6: n/a | F6: DEFER iOS | G6: The largest single lever in the budget. Play Store production access already needs 12 testers running the app for 14 consecutive days plus a review; adding Apple's D-U-N-S wait (5–14 days) on top makes 30 September unreachable. Deferring costs Chokro no iOS users at pilot scale, where the users are students and ward residents on Android.
A7: 2 — Migrate Cloudinary → Firebase Storage | B7: =6*Assumptions!$B$17 -> 28500 | C7: ='2 Technology'!B22-$B$5 -> 12047.79 | D7: =C7*10-B7 -> 91977.9 | E7: =IFERROR(B7/C7,0) -> 2.3655791 | F7: SCHEDULE FOR OCTOBER | G7: Cloudinary is roughly two thirds of the monthly stack. Six days of work removes it and pays back in under three months. Deliberately NOT before launch: those six days would come out of the 35 that must happen by 30 September. The real work is pre-generating image derivatives — Firebase Storage cannot resize on the fly, and without derivatives egress rises about 30× because every thumbnail pulls the full original.
A8: 3 — Replace Groq with Gemini 2.5 Flash-Lite (paid) | B8: =3*Assumptions!$B$17 -> 14250 | C8: 1285 | D8: =C8*12-B8 -> 1170 | E8: =IFERROR(B8/C8,0) -> 11.089494 | F8: DO BEFORE LAUNCH | G8: Already inside the funded $400 package. The money is the least of it: Groq's vision model is PREVIEW-grade with no production equivalent in Groq's catalogue, and Gemini's paid tier is a consent requirement — on the unpaid tier Google may have human reviewers read submitted content, and Chokro submits user photographs tied to GPS and identity. Gemini's responseSchema also enforces the verdict shape, which cuts malformed results that would otherwise each become a paid manual review.
A9: 4 — File the trademark চক্র / Chokro | B9: ='1 Registration'!B24 -> 8500 | C9: 0 | D9: =B9 -> 8500 | E9: n/a | F9: FILE BEFORE FIRST SPONSOR | G9: A sponsor is buying association with a name. Filing after a sponsor logo is live means negotiating from a weaker position if someone else has filed in the meantime. ৳8,500 against a four-figure sponsorship is not a real cost.
A10: 5 — Register as a private limited company instead | B10: 25000 | C10: 0 | D10: =B10 -> 25000 | E10: n/a | F10: REVISIT BEFORE FIRST EPR CONTRACT | G10: Sole proprietorship is right for a pilot and is what this budget assumes. But it gives no liability separation, and corporate procurement — exactly who signs EPR compliance contracts — generally prefers a limited company. The trigger for revisiting is the first real contract, not a date.
A12: Payback is in months, and is the one-off cost divided by the monthly saving. Levers 1, 4 and 5 have no monthly saving, so payback does not apply to them.

Sheet Risks
A1: Budget Risks
A2: Only risks with a money consequence. Product and schedule risks live in the launch planner.
A4: Risk | B4: Exposure (৳) | C4: Exposure ($) | D4: Window | E4: Mitigation and detail
A5: Cloudinary soft-limit disables the account | B5: 0 | C5: =B5/Assumptions!$B$6 -> 0 | D5: From launch | E5: Cloudinary's tiers are SOFT-limit: exceeding credits does not bill overage, it warns and then disables the account. On a live app every image stops loading at once, with no pay-as-you-go safety valve. Direct budget exposure is ৳0, which is exactly what makes it dangerous. The pilot already consumes about 63 of the free tier's 25 credits in month one, so Plus is budgeted from launch. MITIGATION: monitor credits weekly; lever 2 removes the dependency entirely.
A6: Taka depreciates 10% against the dollar | B6: =0.1*('2 Technology'!B9+'2 Technology'!B29) -> 22759.351 | C6: =B6/Assumptions!$B$6 -> 184.72 | D6: Any time | E6: About 79% of year-one spend is USD-billed on an international card. A 10% move costs the amount shown, and it arrives silently across twelve card statements. MITIGATION: the exchange rate is a single input cell — re-price quarterly. Levers 2 and 3 consolidate four USD vendors down to two, which also reduces card and forex friction.
A7: 24 unfunded days rest on one person | B7: ='3 People'!C24 -> 114000 | C7: =B7/Assumptions!$B$6 -> 925.24957 | D7: September | E7: The amount shown is what it would cost to backfill those days at the mid rate if Arnish is unavailable — illness, coursework, anything. There is no redundancy in the plan. MITIGATION: the $400 was pointed at the lanes that cannot be fixed after launch, so a slip delays polish rather than exposing users.
A8: Play production access delays the launch | B8: ='2 Technology'!B28 -> 18709.439 | C8: =B8/Assumptions!$B$6 -> 151.85 | D8: Sep–Oct | E8: Google Play accounts created after Nov 2023 need 12 testers running the app for 14 consecutive days, then a production-access review — realistically 2–4 weeks. The exposure shown is one month of run rate burned with no launch. MITIGATION: start the tester cohort immediately; it is free and it is the longest lead time in the plan.
A9: Firebase Auth crosses the 50k MAU free tier | B9: =505*Assumptions!$B$6 -> 62221.05 | C9: =B9/Assumptions!$B$6 -> 505 | D9: Year 2 | E9: Auth is free to 50,000 monthly active users, then $0.0055 each. At 150k MAU that is about $505 a month, appearing in one billing cycle. ৳0 in this budget and the largest single new line in next year's. MITIGATION: model it into the year-2 plan before the city-scale rollout, not after.
A10: rateLimit.js counters are per-process | B10: =10*'2 Technology'!B23 -> 2402.595 | C10: =B10/Assumptions!$B$6 -> 19.5 | D10: On scaling out | E10: The rate limiter holds its counters in process memory — its own code comment says so. A second server instance doubles every limit and removes the ceiling on AI spend; the exposure shown is a 10× overrun on the screening line. MITIGATION: shared Redis before a second instance ever runs. Upstash's free tier covers pilot volume, so this is engineering time, not budget.

Sheet Sources
A1: Sources
A2: Every figure in this workbook, where it came from, and how much to trust it.
A4: Figure | B4: Value | C4: Checked | D4: Source | E4: Confidence
A5: DNCC trade licence, category 253 · signboard tax · VAT · source tax | B5: ৳2,000 · 480 · 372 · 3,000 | C5: 2 Sep 2026 | D5: Arnish, supplied directly. VAT reproduced as 15% of licence + signboard. | E5: Supplied by client
A6: Licence book/form · documentation | B6: ৳270–500 · 200–500 | C6: 2 Sep 2026 | D6: Arnish, supplied as ranges. Midpoints used. | E6: Supplied by client
A7: Bank account minimum balance | B7: ৳2,000 | C7: 2 Sep 2026 | D7: Typical Bangladeshi current-account minimum. | E7: Estimate — confirm with bank
A8: Trademark, one class | B8: ৳8,500 | C8: 2 Sep 2026 | D8: ≈৳3,500 DPDT government fee plus ≈৳5,000 agent fee. | E8: Estimate — not quoted
A9: Private limited incorporation | B9: ৳25,000 | C9: 2 Sep 2026 | D9: RJSC name clearance, stamp duty and agent fees, mid-range for modest authorised capital. | E9: Estimate — not quoted
A10: Google Play developer account | B10: $25 one-time | C10: 30 Aug 2026 | D10: Google Play Console published price. | E10: Vendor published
A11: Apple Developer Program | B11: $99 / year | C11: 30 Aug 2026 | D11: Apple Developer published price. | E11: Vendor published
A12: .com · .com.bd domains | B12: ৳1,199 · ৳2,500 / yr | C12: 30 Aug 2026 | D12: Local registrar · BTCL. | E12: Vendor published
A13: Cloudinary Plus | B13: $99 / month, 225 credits | C13: 30 Aug 2026 | D13: Cloudinary published pricing. Free tier 25 credits; Advanced $249/600. | E13: Vendor published
A14: Gemini 2.5 Flash-Lite | B14: $0.00026 / screening | C14: 30 Aug 2026 | D14: Google Vertex AI published token pricing at 2,000 in + 150 out per call. | E14: Vendor published
A15: Render app server | B15: $25 / month (Starter) | C15: 30 Aug 2026 | D15: Render published pricing. Pro $85. | E15: Vendor published
... A24: Cloudinary replacement cost after migration | B24: ৳150 / month | C24: 2 Sep 2026 | D24: Firebase Storage plus CDN at pilot volume. | E24: Estimate
A26: Read the confidence column before quoting any figure externally. 'Vendor published' and 'Measured' are solid. 'Supplied by client' means Arnish provided it and it has not been independently verified against a ward-office schedule. 'Estimate' means nobody has been quoted yet — three of these (the Mac, the trademark and private-limited incorporation) are large enough that a real quote should replace the estimate before this budget is committed.
